bb_ipythontools/__init__.py
bb_ipythontools/datafiles/__init__.py
bb_ipythontools/datafiles/ipython_config.py
bb_ipythontools/ipythonprojectfunctions.py
bb_ipythontools-0.0.2.dist-info/METADATA
bb_ipythontools-0.0.2.dist-info/WHEEL
bb_ipythontools-0.0.2.dist-info/RECORD
