Metadata-Version: 2.1
Name: bb-ipythontools
Version: 0.0.2
Summary: 
Author: Erik Beebe
Author-email: beebeapps_debugging@tuta.io
Requires-Python: >=3.10,<4.0
Classifier: Programming Language :: Python :: 3
Classifier: Programming Language :: Python :: 3.10
Classifier: Programming Language :: Python :: 3.11
